durusai/__init__.py
durusai/__main__.py
durusai/api_client.py
durusai/auth.py
durusai/cli.py
durusai/config.py
durusai/exceptions.py
durusai/interactive.py
durusai/local_file_ops.py
durusai/simple_console.py
durusai/updater.py
durusai_cli-3.5.1.dist-info/METADATA
durusai_cli-3.5.1.dist-info/WHEEL
durusai_cli-3.5.1.dist-info/entry_points.txt
durusai_cli-3.5.1.dist-info/top_level.txt
durusai_cli-3.5.1.dist-info/RECORD
