Metadata-Version: 2.4
Name: durusai-cli
Version: 3.5.1
Summary: DurusAI CLI - Advanced AI assistant with memory, file operations, and project management like Claude Code
Home-page: https://github.com/durusai/cli
Author: DurusAI Team
Author-email: DurusAI Team <support@durusai.com>
Maintainer-email: DurusAI Team <support@durusai.com>
Project-URL: Homepage, https://durusai.com
Project-URL: Documentation, https://docs.durusai.com
Project-URL: Repository, https://github.com/durusai/cli
Project-URL: Bug Tracker, https://github.com/durusai/cli/issues
Project-URL: Changelog, https://github.com/durusai/cli/blob/main/CHANGELOG.md
Keywords: ai,cli,assistant,development,api,anthropic,openai,terminal
Classifier: Development Status :: 4 - Beta
Classifier: Intended Audience :: Developers
Classifier: License :: OSI Approved :: MIT License
Classifier: Operating System :: OS Independent
Classifier: Programming Language :: Python :: 3
Classifier: Programming Language :: Python :: 3.8
Classifier: Programming Language :: Python :: 3.9
Classifier: Programming Language :: Python :: 3.10
Classifier: Programming Language :: Python :: 3.11
Classifier: Programming Language :: Python :: 3.12
Classifier: Topic :: Software Development :: Libraries :: Python Modules
Classifier: Topic :: Terminals
Classifier: Topic :: Utilities
Classifier: Environment :: Console
Requires-Python: >=3.8
Requires-Dist: typer[all]>=0.9.0
Requires-Dist: rich>=13.0.0
Requires-Dist: httpx>=0.24.0
Requires-Dist: prompt-toolkit>=3.0.0
Requires-Dist: keyring>=24.0.0
Requires-Dist: cryptography>=40.0.0
Requires-Dist: PyJWT>=2.8.0
Requires-Dist: markdown>=3.4.0
Requires-Dist: packaging>=21.0
Provides-Extra: dev
Requires-Dist: pytest>=7.0.0; extra == "dev"
Requires-Dist: pytest-asyncio>=0.21.0; extra == "dev"
Requires-Dist: black>=23.0.0; extra == "dev"
Requires-Dist: flake8>=6.0.0; extra == "dev"
Requires-Dist: mypy>=1.0.0; extra == "dev"
Requires-Dist: build>=0.10.0; extra == "dev"
Requires-Dist: twine>=4.0.0; extra == "dev"
Provides-Extra: full
Requires-Dist: psutil>=5.9.0; extra == "full"
Requires-Dist: python-dotenv>=1.0.0; extra == "full"
Dynamic: author
Dynamic: home-page
Dynamic: requires-python
